AUTHORS.rst
CONTRIBUTING.rst
HISTORY.rst
LICENSE
MANIFEST.in
README.rst
setup.cfg
setup.py
docs/Makefile
docs/authors.rst
docs/conf.py
docs/contributing.rst
docs/history.rst
docs/index.rst
docs/installation.rst
docs/make.bat
docs/modules.rst
docs/pygmyhdl.rst
docs/readme.rst
docs/usage.rst
pygmyhdl/__init__.py
pygmyhdl/gates.py
pygmyhdl/pckg_info.py
pygmyhdl/pygmyhdl.py
pygmyhdl.egg-info/PKG-INFO
pygmyhdl.egg-info/SOURCES.txt
pygmyhdl.egg-info/dependency_links.txt
pygmyhdl.egg-info/entry_points.txt
pygmyhdl.egg-info/not-zip-safe
pygmyhdl.egg-info/requires.txt
pygmyhdl.egg-info/top_level.txt
tests/.gitignore