Metadata-Version: 1.1
Name: pygmyhdl
Version: 0.0.4
Summary: MyHDL hardware design language encased in the tasty PygMyHDL wrapper.
Home-page: https://github.com/devbisme/pygmyhdl
Author: Dave Vandenbout
Author-email: devb@xess.com
License: MIT
Keywords: pygmyhdl
Platform: UNKNOWN
Classifier: Development Status :: 3 - Alpha
Classifier: Intended Audience :: Developers
Classifier: Intended Audience :: Science/Research
Classifier: Topic :: Scientific/Engineering :: Electronic Design Automation (EDA)
Classifier: License :: OSI Approved :: MIT License
Classifier: Natural Language :: English
Classifier: Programming Language :: Python :: 2.7
Classifier: Programming Language :: Python :: 3.5
